<?xml version="1.0" encoding="UTF-8" standalone="yes"?>
<contentHaul xmlns:a="http://www.appian.com/ae/types/2009">
    <versionUuid>_a-0000e0cb-9c1d-8000-29b4-01ef9001ef90_22520</versionUuid>
    <constant>
        <name>QACC_QUICK_APP_CALLED_CRAP_RECORD_TYPE</name>
        <uuid>_a-0000e0cb-9c1d-8000-29b4-01ef9001ef90_21961</uuid>
        <description>Record type for Quick App Called Crap. Used for links, record tags in news, and record pickers. [Records]</description>
        <parentUuid>c2b7d266-2844-4432-bc65-200cc7c30ca3</parentUuid>
        <visibility>
            <advertise>false</advertise>
            <hierarchy>true</hierarchy>
            <indexable>true</indexable>
            <quota>false</quota>
            <searchable>true</searchable>
            <system>false</system>
            <unlogged>false</unlogged>
        </visibility>
        <typedValue>
            <type>
                <name>RecordType</name>
                <namespace>http://www.appian.com/ae/types/2009</namespace>
            </type>
            <value a:id="-1" a:uuid="d9bb2f83-3877-4b57-8303-c29d65b2743d" name="">
                <a:isSystem>false</a:isSystem>
                <a:security>16383</a:security>
            </value>
        </typedValue>
        <isEnvironmentSpecific>false</isEnvironmentSpecific>
    </constant>
    <roleMap public="true">
        <role inherit="true" allowForAll="false" name="readers">
            <users/>
            <groups/>
        </role>
        <role inherit="true" allowForAll="false" name="authors">
            <users/>
            <groups/>
        </role>
        <role inherit="true" allowForAll="false" name="administrators">
            <users/>
            <groups/>
        </role>
        <role inherit="false" allowForAll="false" name="denyReaders">
            <users/>
            <groups/>
        </role>
        <role inherit="false" allowForAll="false" name="denyAuthors">
            <users/>
            <groups/>
        </role>
        <role inherit="false" allowForAll="false" name="denyAdministrators">
            <users/>
            <groups/>
        </role>
    </roleMap>
    <history>
        <historyInfo versionUuid="_a-0000e0cb-9c1d-8000-29b4-01ef9001ef90_22520"/>
    </history>
</contentHaul>
